{
  "streams": [
    {
      "title": "MyStrim",
      "description": "Dis Strimm gret",
      "id": 1
    },
    {
      "title": "MyStrim",
      "description": "Dis Strimm gre",
      "id": 2
    },
    {
      "title": "Other Strimm",
      "description": "Hi strimm",
      "id": 3
    },
    {
      "title": "Hi",
      "description": "Hello yousss",
      "userId": "111895799577312756671",
      "id": 4
    },
    {
      "title": "Unexpected Behaviour",
      "description": "Woah!d",
      "id": 5
    },
    {
      "title": "Unexpected Behaviour",
      "description": "Woah!s",
      "id": 6
    },
    {
      "title": "ddddddsss",
      "description": "aaaaaaaaass",
      "userId": "111895799577312756671",
      "id": 7
    },
    {
      "title": "sss",
      "description": "sddd",
      "userId": "111895799577312756671",
      "id": 8
    }
  ]
}